byAd12/__init__.py
byAd12/byAd12.py
byAd12/byAd12_library.py
byAd12_library-1.2.1.dist-info/METADATA
byAd12_library-1.2.1.dist-info/WHEEL
byAd12_library-1.2.1.dist-info/top_level.txt
byAd12_library-1.2.1.dist-info/RECORD
