Metadata-Version: 2.1
Name: byAd12-library
Version: 1.2.1
Summary: Multi function library.
Home-page: https://github.com/byAd12/byAd12-Library.git
Author: Adrián L. G. P.
Author-email: adgimenezp@gmail.com
Requires-Dist: ping3
